uqlib/__init__.py
uqlib-0.0.0.dist-info/METADATA
uqlib-0.0.0.dist-info/WHEEL
uqlib-0.0.0.dist-info/top_level.txt
uqlib-0.0.0.dist-info/RECORD
