Metadata-Version: 2.1
Name: uqlib
Version: 0.0.0
Summary: Coming soon
Author-email: Samuel Duffield <sam@normalcomputing.ai>
